sabemos/__init__.py
sabemos-0.0.2.dist-info/LICENSE
sabemos-0.0.2.dist-info/METADATA
sabemos-0.0.2.dist-info/WHEEL
sabemos-0.0.2.dist-info/top_level.txt
sabemos-0.0.2.dist-info/RECORD
