Metadata-Version: 2.1
Name: sabemos
Version: 0.0.2
Summary: A cloud-native self-hosting-friendly Q&A application
Author-email: Rainer Schwarzbach <undisclosed@example.com>
License: MIT License
Project-URL: homepage, https://gitlab.com/blackstream-x/sabemos
Project-URL: documentation, https://blackstream-x.gitlab.io/sabemos
Project-URL: repository, https://gitlab.com/blackstream-x/sabemos.git
Project-URL: Bug Tracker, https://gitlab.com/blackstream-x/sabemos/-/issues
Keywords: questions,answers,knowledge base
Classifier: Development Status :: 1 - Planning
Classifier: Environment :: Web Environment
Classifier: Framework :: Flask
Classifier: Intended Audience :: End Users/Desktop
Classifier: Intended Audience :: System Administrators
Classifier: License :: OSI Approved :: MIT License
Classifier: Operating System :: OS Independent
Classifier: Programming Language :: Python :: 3
Classifier: Programming Language :: Python :: 3.8
Classifier: Programming Language :: Python :: 3.9
Classifier: Programming Language :: Python :: 3.10
Classifier: Programming Language :: Python :: 3.11
Classifier: Programming Language :: Python :: 3 :: Only
Classifier: Natural Language :: English
Classifier: Topic :: Documentation
Classifier: Topic :: Office/Business :: Groupware
Requires-Python: >=3.8
License-File: LICENSE
Requires-Dist: Flask
Requires-Dist: oic
Requires-Dist: PyYaml
Requires-Dist: SQLAlchemy
